chronovoyage/__about__.py
chronovoyage/__init__.py
chronovoyage/__main__.py
chronovoyage/logging.yaml
chronovoyage/py.typed
chronovoyage/cli/__init__.py
chronovoyage/domain/__init__.py
chronovoyage/domain/add.py
chronovoyage/domain/current.py
chronovoyage/domain/init.py
chronovoyage/domain/migrate.py
chronovoyage/domain/rollback.py
chronovoyage/internal/__init__.py
chronovoyage/internal/config.py
chronovoyage/internal/database/__init__.py
chronovoyage/internal/database/connection.py
chronovoyage/internal/database/connection.pyi
chronovoyage/internal/database/mariadb_.py
chronovoyage/internal/exception/__init__.py
chronovoyage/internal/exception/config.py
chronovoyage/internal/exception/database.py
chronovoyage/internal/exception/domain.py
chronovoyage/internal/exception/enum.py
chronovoyage/internal/exception/feature.py
chronovoyage/internal/feature/__init__.py
chronovoyage/internal/feature/flags.py
chronovoyage/internal/feature/flags.pyi
chronovoyage/internal/interface/__init__.py
chronovoyage/internal/interface/database.py
chronovoyage/internal/logger/__init__.py
chronovoyage/internal/logger/handler.py
chronovoyage/internal/logger/logger.py
chronovoyage/internal/logger/logger.pyi
chronovoyage/internal/type/__init__.py
chronovoyage/internal/type/config.py
chronovoyage/internal/type/database.py
chronovoyage/internal/type/dict.py
chronovoyage/internal/type/enum.py
chronovoyage/lib/__init__.py
chronovoyage/lib/datetime_time.py
chronovoyage/usecase/__init__.py
chronovoyage/usecase/current.py
chronovoyage/usecase/init.py
chronovoyage/usecase/migrate.py
chronovoyage/usecase/rollback.py
chronovoyage-0.2.2.dist-info/METADATA
chronovoyage-0.2.2.dist-info/WHEEL
chronovoyage-0.2.2.dist-info/entry_points.txt
chronovoyage-0.2.2.dist-info/licenses/LICENSE.txt
chronovoyage-0.2.2.dist-info/RECORD
