Metadata-Version: 2.3
Name: chronovoyage
Version: 0.2.2
Summary: Simple database migration framework.
Project-URL: Documentation, https://chronovoyagemigration.net/
Project-URL: Issues, https://github.com/fairy-select/chronovoyage/issues
Project-URL: Source, https://github.com/fairy-select/chronovoyage
Author-email: Noritaka IZUMI <noritaka.izumi@gmail.com>
License: MIT License
Keywords: database,migration
Classifier: Development Status :: 4 - Beta
Classifier: License :: OSI Approved :: MIT License
Classifier: Programming Language :: Python
Classifier: Programming Language :: Python :: 3.8
Classifier: Programming Language :: Python :: 3.9
Classifier: Programming Language :: Python :: 3.10
Classifier: Programming Language :: Python :: 3.11
Classifier: Programming Language :: Python :: 3.12
Classifier: Programming Language :: Python :: 3.13
Classifier: Programming Language :: Python :: Implementation :: CPython
Classifier: Programming Language :: Python :: Implementation :: PyPy
Classifier: Topic :: Database
Requires-Python: >=3.8
Requires-Dist: click
Requires-Dist: python-dotenv
Requires-Dist: pyyaml
Requires-Dist: typing-extensions
Provides-Extra: mariadb
Requires-Dist: mariadb; extra == 'mariadb'
